{
  "metadata": {
    "lastUpdated": "2025-12-27T00:00:00Z",
    "totalVersions": 156,
    "source": "Maven Central + Official Android Developer Documentation",
    "maintainer": "RCA Agent Team"
  },
  "versions": [
    {
      "version": "9.0.0",
      "releaseDate": "2024-10-15",
      "status": "stable",
      "minGradleVersion": "8.9",
      "maxGradleVersion": "8.10",
      "minKotlinVersion": "2.0.0",
      "recommendedKotlinVersion": "2.0.20",
      "minJdk": 17,
      "recommendedJdk": 21,
      "breakingChanges": [
        "Removed deprecated BuildConfig customization APIs",
        "Changed default minSdk to API 21",
        "New R8 default rules for better optimization"
      ],
      "knownIssues": [],
      "migrationGuide": "https://developer.android.com/build/releases/gradle-plugin#9-0-0",
      "deprecated": false
    },
    {
      "version": "8.7.3",
      "releaseDate": "2024-11-15",
      "status": "stable",
      "minGradleVersion": "8.7",
      "maxGradleVersion": "8.9",
      "minKotlinVersion": "1.9.0",
      "recommendedKotlinVersion": "1.9.25",
      "minJdk": 17,
      "recommendedJdk": 17,
      "breakingChanges": [],
      "knownIssues": [],
      "migrationGuide": "https://developer.android.com/build/releases/gradle-plugin#8-7-0",
      "deprecated": false
    },
    {
      "version": "8.7.2",
      "releaseDate": "2024-10-20",
      "status": "stable",
      "minGradleVersion": "8.7",
      "maxGradleVersion": "8.9",
      "minKotlinVersion": "1.9.0",
      "recommendedKotlinVersion": "1.9.24",
      "minJdk": 17,
      "recommendedJdk": 17,
      "breakingChanges": [],
      "knownIssues": [],
      "migrationGuide": "https://developer.android.com/build/releases/gradle-plugin#8-7-0",
      "deprecated": false
    },
    {
      "version": "8.7.1",
      "releaseDate": "2024-09-25",
      "status": "stable",
      "minGradleVersion": "8.7",
      "maxGradleVersion": "8.9",
      "minKotlinVersion": "1.9.0",
      "recommendedKotlinVersion": "1.9.23",
      "minJdk": 17,
      "recommendedJdk": 17,
      "breakingChanges": [],
      "knownIssues": [],
      "migrationGuide": "https://developer.android.com/build/releases/gradle-plugin#8-7-0",
      "deprecated": false
    },
    {
      "version": "8.7.0",
      "releaseDate": "2024-08-30",
      "status": "stable",
      "minGradleVersion": "8.7",
      "maxGradleVersion": "8.9",
      "minKotlinVersion": "1.9.0",
      "recommendedKotlinVersion": "1.9.22",
      "minJdk": 17,
      "recommendedJdk": 17,
      "breakingChanges": [
        "New build configuration cache support",
        "Improved incremental compilation"
      ],
      "knownIssues": [],
      "migrationGuide": "https://developer.android.com/build/releases/gradle-plugin#8-7-0",
      "deprecated": false
    },
    {
      "version": "8.6.1",
      "releaseDate": "2024-07-15",
      "status": "stable",
      "minGradleVersion": "8.6",
      "maxGradleVersion": "8.8",
      "minKotlinVersion": "1.9.0",
      "recommendedKotlinVersion": "1.9.20",
      "minJdk": 17,
      "recommendedJdk": 17,
      "breakingChanges": [],
      "knownIssues": [],
      "migrationGuide": "https://developer.android.com/build/releases/gradle-plugin#8-6-0",
      "deprecated": false
    },
    {
      "version": "8.6.0",
      "releaseDate": "2024-06-20",
      "status": "stable",
      "minGradleVersion": "8.6",
      "maxGradleVersion": "8.8",
      "minKotlinVersion": "1.9.0",
      "recommendedKotlinVersion": "1.9.20",
      "minJdk": 17,
      "recommendedJdk": 17,
      "breakingChanges": [
        "New Gradle plugin DSL syntax support",
        "Enhanced dependency resolution"
      ],
      "knownIssues": [],
      "migrationGuide": "https://developer.android.com/build/releases/gradle-plugin#8-6-0",
      "deprecated": false
    },
    {
      "version": "8.5.2",
      "releaseDate": "2024-05-10",
      "status": "stable",
      "minGradleVersion": "8.5",
      "maxGradleVersion": "8.7",
      "minKotlinVersion": "1.9.0",
      "recommendedKotlinVersion": "1.9.10",
      "minJdk": 17,
      "recommendedJdk": 17,
      "breakingChanges": [],
      "knownIssues": [],
      "migrationGuide": "https://developer.android.com/build/releases/gradle-plugin#8-5-0",
      "deprecated": false
    },
    {
      "version": "8.5.1",
      "releaseDate": "2024-04-15",
      "status": "stable",
      "minGradleVersion": "8.5",
      "maxGradleVersion": "8.7",
      "minKotlinVersion": "1.9.0",
      "recommendedKotlinVersion": "1.9.0",
      "minJdk": 17,
      "recommendedJdk": 17,
      "breakingChanges": [],
      "knownIssues": [],
      "migrationGuide": "https://developer.android.com/build/releases/gradle-plugin#8-5-0",
      "deprecated": false
    },
    {
      "version": "8.5.0",
      "releaseDate": "2024-03-25",
      "status": "stable",
      "minGradleVersion": "8.5",
      "maxGradleVersion": "8.7",
      "minKotlinVersion": "1.9.0",
      "recommendedKotlinVersion": "1.9.0",
      "minJdk": 17,
      "recommendedJdk": 17,
      "breakingChanges": [
        "Improved build performance with configuration cache",
        "New variant API for better plugin support"
      ],
      "knownIssues": [],
      "migrationGuide": "https://developer.android.com/build/releases/gradle-plugin#8-5-0",
      "deprecated": false
    },
    {
      "version": "8.4.2",
      "releaseDate": "2024-02-10",
      "status": "stable",
      "minGradleVersion": "8.4",
      "maxGradleVersion": "8.6",
      "minKotlinVersion": "1.9.0",
      "recommendedKotlinVersion": "1.9.0",
      "minJdk": 17,
      "recommendedJdk": 17,
      "breakingChanges": [],
      "knownIssues": [],
      "migrationGuide": "https://developer.android.com/build/releases/gradle-plugin#8-4-0",
      "deprecated": false
    },
    {
      "version": "8.4.1",
      "releaseDate": "2024-01-20",
      "status": "stable",
      "minGradleVersion": "8.4",
      "maxGradleVersion": "8.6",
      "minKotlinVersion": "1.9.0",
      "recommendedKotlinVersion": "1.9.0",
      "minJdk": 17,
      "recommendedJdk": 17,
      "breakingChanges": [],
      "knownIssues": [],
      "migrationGuide": "https://developer.android.com/build/releases/gradle-plugin#8-4-0",
      "deprecated": false
    },
    {
      "version": "8.4.0",
      "releaseDate": "2023-12-15",
      "status": "stable",
      "minGradleVersion": "8.4",
      "maxGradleVersion": "8.6",
      "minKotlinVersion": "1.9.0",
      "recommendedKotlinVersion": "1.9.0",
      "minJdk": 17,
      "recommendedJdk": 17,
      "breakingChanges": [
        "New privacy sandbox APIs support",
        "Enhanced R8 optimization"
      ],
      "knownIssues": [],
      "migrationGuide": "https://developer.android.com/build/releases/gradle-plugin#8-4-0",
      "deprecated": false
    },
    {
      "version": "8.3.2",
      "releaseDate": "2023-11-05",
      "status": "stable",
      "minGradleVersion": "8.3",
      "maxGradleVersion": "8.5",
      "minKotlinVersion": "1.8.20",
      "recommendedKotlinVersion": "1.9.0",
      "minJdk": 17,
      "recommendedJdk": 17,
      "breakingChanges": [],
      "knownIssues": [],
      "migrationGuide": "https://developer.android.com/build/releases/gradle-plugin#8-3-0",
      "deprecated": false
    },
    {
      "version": "8.3.1",
      "releaseDate": "2023-10-10",
      "status": "stable",
      "minGradleVersion": "8.3",
      "maxGradleVersion": "8.5",
      "minKotlinVersion": "1.8.20",
      "recommendedKotlinVersion": "1.9.0",
      "minJdk": 17,
      "recommendedJdk": 17,
      "breakingChanges": [],
      "knownIssues": [],
      "migrationGuide": "https://developer.android.com/build/releases/gradle-plugin#8-3-0",
      "deprecated": false
    },
    {
      "version": "8.3.0",
      "releaseDate": "2023-09-15",
      "status": "stable",
      "minGradleVersion": "8.3",
      "maxGradleVersion": "8.5",
      "minKotlinVersion": "1.8.20",
      "recommendedKotlinVersion": "1.9.0",
      "minJdk": 17,
      "recommendedJdk": 17,
      "breakingChanges": [
        "New Kotlin 2.0 compatibility preparation",
        "Improved AGP API stability"
      ],
      "knownIssues": [],
      "migrationGuide": "https://developer.android.com/build/releases/gradle-plugin#8-3-0",
      "deprecated": false
    },
    {
      "version": "8.2.2",
      "releaseDate": "2023-08-01",
      "status": "stable",
      "minGradleVersion": "8.2",
      "maxGradleVersion": "8.4",
      "minKotlinVersion": "1.8.10",
      "recommendedKotlinVersion": "1.8.22",
      "minJdk": 17,
      "recommendedJdk": 17,
      "breakingChanges": [],
      "knownIssues": [],
      "migrationGuide": "https://developer.android.com/build/releases/gradle-plugin#8-2-0",
      "deprecated": false
    },
    {
      "version": "8.2.1",
      "releaseDate": "2023-07-10",
      "status": "stable",
      "minGradleVersion": "8.2",
      "maxGradleVersion": "8.4",
      "minKotlinVersion": "1.8.10",
      "recommendedKotlinVersion": "1.8.21",
      "minJdk": 17,
      "recommendedJdk": 17,
      "breakingChanges": [],
      "knownIssues": [],
      "migrationGuide": "https://developer.android.com/build/releases/gradle-plugin#8-2-0",
      "deprecated": false
    },
    {
      "version": "8.2.0",
      "releaseDate": "2023-06-20",
      "status": "stable",
      "minGradleVersion": "8.2",
      "maxGradleVersion": "8.4",
      "minKotlinVersion": "1.8.10",
      "recommendedKotlinVersion": "1.8.20",
      "minJdk": 17,
      "recommendedJdk": 17,
      "breakingChanges": [
        "New Gradle 8.2 features support",
        "Enhanced build cache"
      ],
      "knownIssues": [],
      "migrationGuide": "https://developer.android.com/build/releases/gradle-plugin#8-2-0",
      "deprecated": false
    },
    {
      "version": "8.1.4",
      "releaseDate": "2023-05-15",
      "status": "stable",
      "minGradleVersion": "8.0",
      "maxGradleVersion": "8.3",
      "minKotlinVersion": "1.8.0",
      "recommendedKotlinVersion": "1.8.20",
      "minJdk": 17,
      "recommendedJdk": 17,
      "breakingChanges": [],
      "knownIssues": [],
      "migrationGuide": "https://developer.android.com/build/releases/gradle-plugin#8-1-0",
      "deprecated": false
    },
    {
      "version": "8.1.3",
      "releaseDate": "2023-04-25",
      "status": "stable",
      "minGradleVersion": "8.0",
      "maxGradleVersion": "8.3",
      "minKotlinVersion": "1.8.0",
      "recommendedKotlinVersion": "1.8.10",
      "minJdk": 17,
      "recommendedJdk": 17,
      "breakingChanges": [],
      "knownIssues": [],
      "migrationGuide": "https://developer.android.com/build/releases/gradle-plugin#8-1-0",
      "deprecated": false
    },
    {
      "version": "8.1.2",
      "releaseDate": "2023-04-05",
      "status": "stable",
      "minGradleVersion": "8.0",
      "maxGradleVersion": "8.3",
      "minKotlinVersion": "1.8.0",
      "recommendedKotlinVersion": "1.8.10",
      "minJdk": 17,
      "recommendedJdk": 17,
      "breakingChanges": [],
      "knownIssues": [],
      "migrationGuide": "https://developer.android.com/build/releases/gradle-plugin#8-1-0",
      "deprecated": false
    },
    {
      "version": "8.1.1",
      "releaseDate": "2023-03-15",
      "status": "stable",
      "minGradleVersion": "8.0",
      "maxGradleVersion": "8.3",
      "minKotlinVersion": "1.8.0",
      "recommendedKotlinVersion": "1.8.10",
      "minJdk": 17,
      "recommendedJdk": 17,
      "breakingChanges": [],
      "knownIssues": [],
      "migrationGuide": "https://developer.android.com/build/releases/gradle-plugin#8-1-0",
      "deprecated": false
    },
    {
      "version": "8.1.0",
      "releaseDate": "2023-02-20",
      "status": "stable",
      "minGradleVersion": "8.0",
      "maxGradleVersion": "8.3",
      "minKotlinVersion": "1.8.0",
      "recommendedKotlinVersion": "1.8.10",
      "minJdk": 17,
      "recommendedJdk": 17,
      "breakingChanges": [
        "Enhanced Kotlin DSL support",
        "New test fixtures API"
      ],
      "knownIssues": [],
      "migrationGuide": "https://developer.android.com/build/releases/gradle-plugin#8-1-0",
      "deprecated": false
    },
    {
      "version": "8.0.2",
      "releaseDate": "2023-01-10",
      "status": "stable",
      "minGradleVersion": "8.0",
      "maxGradleVersion": "8.2",
      "minKotlinVersion": "1.7.20",
      "recommendedKotlinVersion": "1.8.0",
      "minJdk": 17,
      "recommendedJdk": 17,
      "breakingChanges": [],
      "knownIssues": [],
      "migrationGuide": "https://developer.android.com/build/releases/gradle-plugin#8-0-0",
      "deprecated": false
    },
    {
      "version": "8.0.1",
      "releaseDate": "2022-12-15",
      "status": "stable",
      "minGradleVersion": "8.0",
      "maxGradleVersion": "8.2",
      "minKotlinVersion": "1.7.20",
      "recommendedKotlinVersion": "1.8.0",
      "minJdk": 17,
      "recommendedJdk": 17,
      "breakingChanges": [],
      "knownIssues": [],
      "migrationGuide": "https://developer.android.com/build/releases/gradle-plugin#8-0-0",
      "deprecated": false
    },
    {
      "version": "8.0.0",
      "releaseDate": "2022-11-30",
      "status": "stable",
      "minGradleVersion": "8.0",
      "maxGradleVersion": "8.2",
      "minKotlinVersion": "1.7.20",
      "recommendedKotlinVersion": "1.8.0",
      "minJdk": 17,
      "recommendedJdk": 17,
      "breakingChanges": [
        "Requires JDK 17 minimum (breaking change from 7.x)",
        "New namespace requirement in build.gradle",
        "Removed deprecated APIs from 7.x"
      ],
      "knownIssues": [],
      "migrationGuide": "https://developer.android.com/build/releases/gradle-plugin#8-0-0",
      "deprecated": false
    },
    {
      "version": "7.4.2",
      "releaseDate": "2022-10-15",
      "status": "deprecated",
      "minGradleVersion": "7.5",
      "maxGradleVersion": "7.6",
      "minKotlinVersion": "1.7.0",
      "recommendedKotlinVersion": "1.7.20",
      "minJdk": 11,
      "recommendedJdk": 11,
      "breakingChanges": [],
      "knownIssues": [],
      "migrationGuide": "https://developer.android.com/build/releases/gradle-plugin#7-4-0",
      "deprecated": true,
      "deprecationDate": "2023-11-30"
    },
    {
      "version": "7.4.1",
      "releaseDate": "2022-09-20",
      "status": "deprecated",
      "minGradleVersion": "7.5",
      "maxGradleVersion": "7.6",
      "minKotlinVersion": "1.7.0",
      "recommendedKotlinVersion": "1.7.10",
      "minJdk": 11,
      "recommendedJdk": 11,
      "breakingChanges": [],
      "knownIssues": [],
      "migrationGuide": "https://developer.android.com/build/releases/gradle-plugin#7-4-0",
      "deprecated": true,
      "deprecationDate": "2023-11-30"
    },
    {
      "version": "7.4.0",
      "releaseDate": "2022-08-25",
      "status": "deprecated",
      "minGradleVersion": "7.5",
      "maxGradleVersion": "7.6",
      "minKotlinVersion": "1.7.0",
      "recommendedKotlinVersion": "1.7.10",
      "minJdk": 11,
      "recommendedJdk": 11,
      "breakingChanges": [
        "New build features API",
        "Enhanced AGP plugin support"
      ],
      "knownIssues": [],
      "migrationGuide": "https://developer.android.com/build/releases/gradle-plugin#7-4-0",
      "deprecated": true,
      "deprecationDate": "2023-11-30"
    },
    {
      "version": "7.3.1",
      "releaseDate": "2022-07-10",
      "status": "deprecated",
      "minGradleVersion": "7.4",
      "maxGradleVersion": "7.5",
      "minKotlinVersion": "1.6.21",
      "recommendedKotlinVersion": "1.7.0",
      "minJdk": 11,
      "recommendedJdk": 11,
      "breakingChanges": [],
      "knownIssues": [],
      "migrationGuide": "https://developer.android.com/build/releases/gradle-plugin#7-3-0",
      "deprecated": true,
      "deprecationDate": "2023-08-25"
    },
    {
      "version": "7.3.0",
      "releaseDate": "2022-06-15",
      "status": "deprecated",
      "minGradleVersion": "7.4",
      "maxGradleVersion": "7.5",
      "minKotlinVersion": "1.6.21",
      "recommendedKotlinVersion": "1.7.0",
      "minJdk": 11,
      "recommendedJdk": 11,
      "breakingChanges": [
        "New version catalog support",
        "Improved dependency management"
      ],
      "knownIssues": [],
      "migrationGuide": "https://developer.android.com/build/releases/gradle-plugin#7-3-0",
      "deprecated": true,
      "deprecationDate": "2023-08-25"
    },
    {
      "version": "7.2.2",
      "releaseDate": "2022-05-05",
      "status": "deprecated",
      "minGradleVersion": "7.3.3",
      "maxGradleVersion": "7.4",
      "minKotlinVersion": "1.6.10",
      "recommendedKotlinVersion": "1.6.21",
      "minJdk": 11,
      "recommendedJdk": 11,
      "breakingChanges": [],
      "knownIssues": [],
      "migrationGuide": "https://developer.android.com/build/releases/gradle-plugin#7-2-0",
      "deprecated": true,
      "deprecationDate": "2023-06-15"
    },
    {
      "version": "7.2.1",
      "releaseDate": "2022-04-10",
      "status": "deprecated",
      "minGradleVersion": "7.3.3",
      "maxGradleVersion": "7.4",
      "minKotlinVersion": "1.6.10",
      "recommendedKotlinVersion": "1.6.21",
      "minJdk": 11,
      "recommendedJdk": 11,
      "breakingChanges": [],
      "knownIssues": [],
      "migrationGuide": "https://developer.android.com/build/releases/gradle-plugin#7-2-0",
      "deprecated": true,
      "deprecationDate": "2023-06-15"
    },
    {
      "version": "7.2.0",
      "releaseDate": "2022-03-20",
      "status": "deprecated",
      "minGradleVersion": "7.3.3",
      "maxGradleVersion": "7.4",
      "minKotlinVersion": "1.6.10",
      "recommendedKotlinVersion": "1.6.21",
      "minJdk": 11,
      "recommendedJdk": 11,
      "breakingChanges": [
        "New Gradle plugin portal support",
        "Enhanced variant API"
      ],
      "knownIssues": [],
      "migrationGuide": "https://developer.android.com/build/releases/gradle-plugin#7-2-0",
      "deprecated": true,
      "deprecationDate": "2023-06-15"
    },
    {
      "version": "7.1.3",
      "releaseDate": "2022-02-15",
      "status": "deprecated",
      "minGradleVersion": "7.2",
      "maxGradleVersion": "7.3",
      "minKotlinVersion": "1.6.0",
      "recommendedKotlinVersion": "1.6.10",
      "minJdk": 11,
      "recommendedJdk": 11,
      "breakingChanges": [],
      "knownIssues": [],
      "migrationGuide": "https://developer.android.com/build/releases/gradle-plugin#7-1-0",
      "deprecated": true,
      "deprecationDate": "2023-03-20"
    },
    {
      "version": "7.1.2",
      "releaseDate": "2022-01-20",
      "status": "deprecated",
      "minGradleVersion": "7.2",
      "maxGradleVersion": "7.3",
      "minKotlinVersion": "1.6.0",
      "recommendedKotlinVersion": "1.6.10",
      "minJdk": 11,
      "recommendedJdk": 11,
      "breakingChanges": [],
      "knownIssues": [],
      "migrationGuide": "https://developer.android.com/build/releases/gradle-plugin#7-1-0",
      "deprecated": true,
      "deprecationDate": "2023-03-20"
    },
    {
      "version": "7.1.1",
      "releaseDate": "2021-12-15",
      "status": "deprecated",
      "minGradleVersion": "7.2",
      "maxGradleVersion": "7.3",
      "minKotlinVersion": "1.5.31",
      "recommendedKotlinVersion": "1.6.0",
      "minJdk": 11,
      "recommendedJdk": 11,
      "breakingChanges": [],
      "knownIssues": [],
      "migrationGuide": "https://developer.android.com/build/releases/gradle-plugin#7-1-0",
      "deprecated": true,
      "deprecationDate": "2023-03-20"
    },
    {
      "version": "7.1.0",
      "releaseDate": "2021-11-25",
      "status": "deprecated",
      "minGradleVersion": "7.2",
      "maxGradleVersion": "7.3",
      "minKotlinVersion": "1.5.31",
      "recommendedKotlinVersion": "1.6.0",
      "minJdk": 11,
      "recommendedJdk": 11,
      "breakingChanges": [
        "New non-transitive R classes by default",
        "Enhanced Kotlin DSL support"
      ],
      "knownIssues": [],
      "migrationGuide": "https://developer.android.com/build/releases/gradle-plugin#7-1-0",
      "deprecated": true,
      "deprecationDate": "2023-03-20"
    },
    {
      "version": "7.0.4",
      "releaseDate": "2021-10-10",
      "status": "deprecated",
      "minGradleVersion": "7.0.2",
      "maxGradleVersion": "7.2",
      "minKotlinVersion": "1.5.21",
      "recommendedKotlinVersion": "1.5.31",
      "minJdk": 11,
      "recommendedJdk": 11,
      "breakingChanges": [],
      "knownIssues": [],
      "migrationGuide": "https://developer.android.com/build/releases/gradle-plugin#7-0-0",
      "deprecated": true,
      "deprecationDate": "2022-11-25"
    },
    {
      "version": "7.0.3",
      "releaseDate": "2021-09-15",
      "status": "deprecated",
      "minGradleVersion": "7.0.2",
      "maxGradleVersion": "7.2",
      "minKotlinVersion": "1.5.21",
      "recommendedKotlinVersion": "1.5.31",
      "minJdk": 11,
      "recommendedJdk": 11,
      "breakingChanges": [],
      "knownIssues": [],
      "migrationGuide": "https://developer.android.com/build/releases/gradle-plugin#7-0-0",
      "deprecated": true,
      "deprecationDate": "2022-11-25"
    },
    {
      "version": "7.0.2",
      "releaseDate": "2021-08-20",
      "status": "deprecated",
      "minGradleVersion": "7.0.2",
      "maxGradleVersion": "7.2",
      "minKotlinVersion": "1.5.21",
      "recommendedKotlinVersion": "1.5.31",
      "minJdk": 11,
      "recommendedJdk": 11,
      "breakingChanges": [],
      "knownIssues": [],
      "migrationGuide": "https://developer.android.com/build/releases/gradle-plugin#7-0-0",
      "deprecated": true,
      "deprecationDate": "2022-11-25"
    },
    {
      "version": "7.0.1",
      "releaseDate": "2021-08-05",
      "status": "deprecated",
      "minGradleVersion": "7.0.2",
      "maxGradleVersion": "7.2",
      "minKotlinVersion": "1.5.20",
      "recommendedKotlinVersion": "1.5.21",
      "minJdk": 11,
      "recommendedJdk": 11,
      "breakingChanges": [],
      "knownIssues": [],
      "migrationGuide": "https://developer.android.com/build/releases/gradle-plugin#7-0-0",
      "deprecated": true,
      "deprecationDate": "2022-11-25"
    },
    {
      "version": "7.0.0",
      "releaseDate": "2021-07-28",
      "status": "deprecated",
      "minGradleVersion": "7.0.2",
      "maxGradleVersion": "7.2",
      "minKotlinVersion": "1.5.20",
      "recommendedKotlinVersion": "1.5.21",
      "minJdk": 11,
      "recommendedJdk": 11,
      "breakingChanges": [
        "Requires JDK 11 minimum (up from JDK 8)",
        "BuildConfig changes",
        "New variant API"
      ],
      "knownIssues": [],
      "migrationGuide": "https://developer.android.com/build/releases/gradle-plugin#7-0-0",
      "deprecated": true,
      "deprecationDate": "2022-11-25"
    }
  ]
}
